manabase_solver/__init__.py
manabase_solver/lands.py
manabase_solver/manabase_solver.py
manabase_solver/manabase_solver_test.py
manabase_solver/py.typed
manabase_solver/remembering_model.py
manabase_solver/remembering_model_test.py
manabase_solver-0.1.3.dist-info/LICENSE
manabase_solver-0.1.3.dist-info/METADATA
manabase_solver-0.1.3.dist-info/WHEEL
manabase_solver-0.1.3.dist-info/top_level.txt
manabase_solver-0.1.3.dist-info/RECORD
