Metadata-Version: 2.1
Name: manabase-solver
Version: 0.1.3
Summary: Magic: the Gathering manabase solver
Author-email: Thomas David Baker <bakert@gmail.com>
License: MIT License
Project-URL: Homepage, https://github.com/bakert/manabase-solver
Project-URL: Repository, https://github.com/bakert/manabase-solver
Project-URL: Issues, https://github.com/bakert/manabase-solver/issues
Keywords: magic,mtg,manabase,solver
Classifier: Development Status :: 3 - Alpha
Classifier: Intended Audience :: Developers
Classifier: Topic :: Games/Entertainment
Classifier: License :: OSI Approved :: MIT License
Classifier: Programming Language :: Python :: 3.12
Classifier: Programming Language :: Python :: 3.11
Classifier: Programming Language :: Python :: 3.10
Requires-Python: >=3.10
License-File: LICENSE
Requires-Dist: more-itertools
Requires-Dist: multiset
Requires-Dist: ortools
